py_amr2fred/__init__.py
py_amr2fred/adjectives.json
py_amr2fred/amr2fred.py
py_amr2fred/couple.py
py_amr2fred/digraph_writer.py
py_amr2fred/glossary.py
py_amr2fred/node.py
py_amr2fred/parser.py
py_amr2fred/propbank.py
py_amr2fred/propbankframematrix340.tsv
py_amr2fred/propbankrolematrixaligned340.tsv
py_amr2fred/rdf_writer.py
py_amr2fred/taf_post_processor.py
py_amr2fred-0.5.0.dist-info/licenses/LICENSE
py_amr2fred-0.5.0.dist-info/METADATA
py_amr2fred-0.5.0.dist-info/WHEEL
py_amr2fred-0.5.0.dist-info/top_level.txt
py_amr2fred-0.5.0.dist-info/RECORD
