Metadata-Version: 2.4
Name: py_amr2fred
Version: 0.5.0
Summary: TEXT to AMR to RDF/OWL translator.
Author-email: Antonello Meloni <antonello.meloni@unica.it>, Alessandro Russo <alessandro.russo@cnr.it>
License-Expression: GPL-3.0-or-later
Project-URL: Homepage, https://github.com/infovillasimius/py_amr2fred
Project-URL: Issues, https://github.com/infovillasimius/py_amr2fred/issues
Classifier: Programming Language :: Python :: 3
Classifier: Operating System :: OS Independent
Requires-Python: >=3.11
License-File: LICENSE
Requires-Dist: rdflib~=7.1.1
Requires-Dist: Unidecode~=1.3.8
Requires-Dist: requests~=2.32.3
Requires-Dist: nltk~=3.9.1
Requires-Dist: SPARQLWrapper~=2.0.0
Requires-Dist: wikimapper~=0.2.0
Requires-Dist: tqdm~=4.67.1
Dynamic: license-file
